sqlalchemy_pydantic_mapper/ObjectMapper.py
sqlalchemy_pydantic_mapper/__init__.py
sqlalchemy_pydantic_mapper-0.4.0.dist-info/licenses/LICENSE
sqlalchemy_pydantic_mapper-0.4.0.dist-info/METADATA
sqlalchemy_pydantic_mapper-0.4.0.dist-info/WHEEL
sqlalchemy_pydantic_mapper-0.4.0.dist-info/top_level.txt
sqlalchemy_pydantic_mapper-0.4.0.dist-info/RECORD
