Metadata-Version: 2.4
Name: sqlalchemy_pydantic_mapper
Version: 0.4.0
Summary: sqlalchemy-pydantic-mapper library for mapping SQLAlchemy models to Pydantic
Author: ItzSkyReed
License: MIT
Project-URL: Homepage, https://github.com/ItzSkyReed/sqlalchemy-pydantic-mapper
Keywords: sqlalchemy,pydantic,mapper,async
Classifier: Programming Language :: Python :: 3.13
Classifier: License :: OSI Approved :: MIT License
Classifier: Operating System :: OS Independent
Classifier: Development Status :: 4 - Beta
Requires-Python: >=3.13
License-File: LICENSE
Requires-Dist: sqlalchemy>=2.0
Requires-Dist: pydantic>=2.0
Provides-Extra: dev
Requires-Dist: ruff; extra == "dev"
Requires-Dist: pytest; extra == "dev"
Requires-Dist: pytest-cov; extra == "dev"
Requires-Dist: anyio; extra == "dev"
Requires-Dist: aiosqlite; extra == "dev"
Dynamic: license-file
